hypergas/__init__.py
hypergas/a_priori_mask.py
hypergas/angles.py
hypergas/cluster.py
hypergas/config.yaml
hypergas/denoise.py
hypergas/emiss.py
hypergas/folium_map.py
hypergas/hsi2rgb.py
hypergas/hyper.py
hypergas/ime_csf.py
hypergas/landmask.py
hypergas/lut_interp.py
hypergas/orthorectification.py
hypergas/plume_utils.py
hypergas/plumeline.py
hypergas/retrieve.py
hypergas/tle.py
hypergas/unit_spectrum.py
hypergas/version.py
hypergas/wind.py
hypergas/app/About.py
hypergas/app/__init__.py
hypergas/app/__main__.py
hypergas/app/requirements.txt
hypergas/app/pages/1_PlumeMarker.py
hypergas/app/pages/2_Emission.py
hypergas/app/pages/__init__.py
hypergas/imgs/arrow.png
hypergas-0.4.0.dist-info/METADATA
hypergas-0.4.0.dist-info/WHEEL
hypergas-0.4.0.dist-info/licenses/LICENSE
hypergas-0.4.0.dist-info/RECORD
